{
    "searchParameters": {
        "q": "PeaceHealth United General Medical Center address",
        "gl": "us",
        "hl": "en",
        "type": "search",
        "num": 5,
        "engine": "google"
    },
    "answerBox": {
        "title": "PeaceHealth United General Medical Center / Address",
        "answer": "2000 Hospital Dr, Sedro-Woolley, WA 98284"
    },
    "organic": [
        {
            "title": "PeaceHealth United General Medical Center",
            "link": "https://www.peacehealth.org/hospitals/peacehealth-united-general-medical-center",
            "snippet": "2000 Hospital Dr Sedro-Woolley, WA 98284 Map and Directions 360-856-6021 Open 24 Hours Patient & Visitor Resources General information Patient information",
            "position": 1
        },
        {
            "title": "Sedro\u2010Woolley | PeaceHealth",
            "link": "https://www.peacehealth.org/locations/sedro-woolley",
            "snippet": "PeaceHealth United General Medical Center 2000 Hospital Dr Sedro-Woolley, WA 98284 Map and Directions 360-856-6021 Find a Location",
            "position": 2
        },
        {
            "title": "PeaceHealth United General Medical Center",
            "link": "http://www.wsha.org/members/peacehealth-united-general-medical-center/",
            "snippet": "2000 Hospital Drive Sedro-Woolley, WA 98284-4327 map/directions. Phone: (360) 856-6021. Fax: (360) 856-7204",
            "position": 3
        },
        {
            "title": "PEACEHEALTH UNITED GENERAL MEDICAL CENTER - Updated ...",
            "link": "https://www.yelp.com/biz/peacehealth-united-general-medical-center-sedro-woolley",
            "snippet": "More info about PeaceHealth United General Medical Center ; 2000 Hospital Dr. Sedro-Woolley, WA 98284 ; (360) 856-6021 ; Visit Website. https://www.peacehealth.org.",
            "position": 4
        },
        {
            "title": "United General Medical Center Foundation | PeaceHealth",
            "link": "https://www.peacehealth.org/foundation/united-general",
            "snippet": "As a 25-bed critical access hospital, United General supports communities throughout Skagit County including Sedro-Woolley, Mt. Vernon, Burlington, and the ...",
            "position": 5
        }
    ],
    "relatedSearches": [
        {
            "query": "peacehealth sedro-woolley phone number"
        },
        {
            "query": "2000 Hospital Dr Sedro-Woolley, WA 98284"
        },
        {
            "query": "PeaceHealth Sedro Woolley fax number"
        },
        {
            "query": "PeaceHealth Bellingham"
        },
        {
            "query": "PeaceHealth hospital"
        },
        {
            "query": "PeaceHealth portal"
        },
        {
            "query": "Peacehealth Sedro Woolley jobs"
        },
        {
            "query": "peacehealth sedro-woolley lab"
        }
    ],
    "credits": 1
}