{
    "searchParameters": {
        "q": "Sunny View Pediatrics address",
        "gl": "us",
        "hl": "en",
        "type": "search",
        "num": 5,
        "engine": "google"
    },
    "organic": [
        {
            "title": "Sunny View Pediatrics - 1273 Burns Way, Kalispell, Montana - Yelp",
            "link": "https://www.yelp.com/biz/sunny-view-pediatrics-kalispell",
            "snippet": "1273 Burns Way. Kalispell, MT 59901 ; (406) 752-8300 ; Visit Website. https://www.krh.org/krhc/krh-family/physician-network/sunny-view-pediatrics ; More Info.",
            "position": 1
        },
        {
            "title": "Sunny View Pediatrics, Kalispell, MT - Healthgrades",
            "link": "https://www.healthgrades.com/group-directory/mt-montana/kalispell/sunny-view-pediatrics-x5sgst",
            "snippet": "Sunny View Pediatrics is a medical group practice located in Kalispell, MT that specializes in Pediatrics and Nursing (Nurse Practitioner).",
            "position": 2
        },
        {
            "title": "Sunny View Pediatrics, 1273 Burns Way, Kalispell, MT 59901, US",
            "link": "https://www.mapquest.com/us/montana/sunny-view-pediatrics-373491468",
            "snippet": "Get more information for Sunny View Pediatrics in Kalispell, MT. See reviews, map, get the address, and find directions.",
            "position": 3
        },
        {
            "title": "Logan Health Children's Primary Care",
            "link": "https://www.logan.org/location/logan-health-childrens-primary-care/",
            "snippet": "Logan Health Children's Primary Care is proud to offer our families the expertise of four experienced pediatricians and a family nurse practitioner.",
            "position": 4
        },
        {
            "title": "Sunny View Pediatrics - Kalispell - MapQuest",
            "link": "https://www.mapquest.com/us/montana/sunny-view-pediatrics-415195763",
            "snippet": "Get more information for Sunny View Pediatrics in Kalispell, MT. See reviews, map, get the address, and find directions.",
            "position": 5
        }
    ],
    "credits": 1
}