{
    "searchParameters": {
        "q": "VA Community Based Outpatient Clinic website",
        "gl": "us",
        "hl": "en",
        "type": "search",
        "num": 5,
        "engine": "google"
    },
    "organic": [
        {
            "title": "Community Care Home - VA.gov",
            "link": "https://www.va.gov/COMMUNITYCARE/",
            "snippet": "VA provides care to Veterans through community providers when VA cannot provide the care needed. Community care is based on specific eligibility requirements.",
            "sitelinks": [
                {
                    "title": "Veteran Care Overview",
                    "link": "https://www.va.gov/COMMUNITYCARE/programs/veterans/index.asp"
                },
                {
                    "title": "Provider Overview",
                    "link": "https://www.va.gov/COMMUNITYCARE/providers/index.asp"
                },
                {
                    "title": "Community Care Network",
                    "link": "https://www.va.gov/COMMUNITYCARE/providers/Community-Care-Network.asp"
                },
                {
                    "title": "Support",
                    "link": "https://www.va.gov/COMMUNITYCARE/about-us/Support.asp"
                }
            ],
            "position": 1
        },
        {
            "title": "Lane A. Evans VA Community Based Outpatient Clinic - VA.gov",
            "link": "https://www.va.gov/iowa-city-health-care/locations/lane-a-evans-va-community-based-outpatient-clinic/",
            "snippet": "Our outpatient clinic offers primary care to help you stay healthy and well throughout your life. Below, you'll find our address and hours, parking and ...",
            "date": "6 days ago",
            "position": 2
        },
        {
            "title": "Find Locations - VA.gov",
            "link": "https://www.va.gov/directory/guide/Findlocations.cfm",
            "snippet": "This site categorizes information for browsing by state and administration, as well as by viewing through an interactive map of the United States.",
            "sitelinks": [
                {
                    "title": "Virginia",
                    "link": "https://www.va.gov/directory/guide/state.asp?dnum=ALL&STATE=VA"
                },
                {
                    "title": "Washington",
                    "link": "https://www.va.gov/directory/guide/state.asp?dnum=ALL&STATE=WA"
                },
                {
                    "title": "Illinois",
                    "link": "https://www.va.gov/directory/guide/state.asp?dnum=ALL&STATE=IL"
                },
                {
                    "title": "New Jersey",
                    "link": "https://www.va.gov/directory/guide/state.asp?dnum=ALL&STATE=NJ"
                }
            ],
            "position": 3
        },
        {
            "title": "Lyle C. Pearson Community Based Outpatient Clinic - VA.gov",
            "link": "https://www.va.gov/minneapolis-health-care/locations/lyle-c-pearson-community-based-outpatient-clinic/",
            "snippet": "Our outpatient clinic provides primary care and specialty health services, including mental health care, radiology, women's health care, and more.",
            "date": "Nov 25, 2024",
            "sitelinks": [
                {
                    "title": "Location and contact information",
                    "link": "https://www.va.gov/minneapolis-health-care/locations/lyle-c-pearson-community-based-outpatient-clinic/#location-and------------contac"
                },
                {
                    "title": "Prepare for your visit",
                    "link": "https://www.va.gov/minneapolis-health-care/locations/lyle-c-pearson-community-based-outpatient-clinic/#prepare-for-your-visit"
                }
            ],
            "position": 4
        },
        {
            "title": "VA.gov Home | Veterans Affairs",
            "link": "https://www.va.gov//",
            "snippet": "Welcome to the official website of the U.S. Department of Veterans Affairs. Discover, apply for, and manage your VA benefits and care.",
            "sitelinks": [
                {
                    "title": "Find VA Locations",
                    "link": "https://www.va.gov/find-locations/"
                },
                {
                    "title": "Contact Us",
                    "link": "https://www.va.gov/contact-us/"
                },
                {
                    "title": "Careers at VA",
                    "link": "https://www.va.gov/jobs/"
                },
                {
                    "title": "Claim or Appeal Status",
                    "link": "https://www.va.gov/claim-or-appeal-status/"
                }
            ],
            "position": 5
        }
    ],
    "relatedSearches": [
        {
            "query": "VA Community Care phone number"
        },
        {
            "query": "VA Community care provider phone number"
        },
        {
            "query": "VA community care provider List"
        },
        {
            "query": "VA community care referral"
        },
        {
            "query": "VA community care providers near me"
        },
        {
            "query": "Optum VA community care phone number"
        },
        {
            "query": "VA Community Care phone number Colorado"
        },
        {
            "query": "VA community care eligibility"
        }
    ],
    "credits": 1
}