{
    "searchParameters": {
        "q": "Santa Rosa Children's Hospital website",
        "gl": "us",
        "hl": "en",
        "type": "search",
        "num": 5,
        "engine": "google"
    },
    "organic": [
        {
            "title": "Santa Rosa | UCSF Benioff Children's Hospitals",
            "link": "https://www.ucsfbenioffchildrens.org/locations/santa-rosa",
            "snippet": "Our pediatric specialty clinics in Santa Rosa offer convenient care for children from UCSF specialists in cardiology, diabetes, gastroenterology, ...",
            "position": 1
        },
        {
            "title": "CHRISTUS Santa Rosa Health System",
            "link": "https://www.christushealth.org/connect/ministries/santa-rosa",
            "snippet": "CHRISTUS Santa Rosa Children's Hospital is dedicated to the treatment of children who suffer from chronic illnesses and cancer.",
            "position": 2
        },
        {
            "title": "The Children's Hospital of San Antonio - CHRISTUS Health",
            "link": "https://www.christushealth.org/locations/childrens-hospital?service=Trauma",
            "snippet": "We offer complete care in one convenient location, while providing you with access to consulting physicians and some of the top pediatric sub-specialists in the ...",
            "position": 3
        },
        {
            "title": "Stanford Medicine Children's Health",
            "link": "https://www.stanfordchildrens.org/en.html",
            "snippet": "Stanford Medicine Children's Health is the only network in the area\u2014and one of the few in the country\u2014exclusively dedicated to pediatric and obstetric care.",
            "sitelinks": [
                {
                    "title": "Find Locations",
                    "link": "https://www.stanfordchildrens.org/en/locations-directions"
                },
                {
                    "title": "Pay Your Bill",
                    "link": "https://www.stanfordchildrens.org/en/patients-families/pay-your-bill.html"
                },
                {
                    "title": "About Us",
                    "link": "https://www.stanfordchildrens.org/en/about.html"
                },
                {
                    "title": "General Pediatrics",
                    "link": "https://www.stanfordchildrens.org/en/services/pediatrics-general.html"
                }
            ],
            "position": 4
        },
        {
            "title": "Pediatric ER in San Antonio | CHRISTUS Children's Hospital",
            "link": "https://christushealth-production-cd.azurewebsites.net/locations/childrens-hospital/emergency-room",
            "snippet": "CHRISTUS Children'sprovides emergency care to newborn babies and kids all the way up to age 17. Our specially trained doctors, nurses, technicians, and child ...",
            "position": 5
        }
    ],
    "relatedSearches": [
        {
            "query": "500 Doyle Park drive Santa Rosa"
        },
        {
            "query": "CHRISTUS Santa Rosa Hospital downtown"
        },
        {
            "query": "333 n santa rosa st, san antonio, tx 78207"
        },
        {
            "query": "CHRISTUS Children's"
        },
        {
            "query": "CHRISTUS Santa Rosa Locations"
        },
        {
            "query": "Children's Hospital near me"
        },
        {
            "query": "Children's hospital of San Antonio"
        },
        {
            "query": "Best Children's hospital in San Antonio"
        }
    ],
    "credits": 1
}