{
    "searchParameters": {
        "q": "Dimond Medical Clinic website",
        "gl": "us",
        "hl": "en",
        "type": "search",
        "num": 5,
        "engine": "google"
    },
    "organic": [
        {
            "title": "Anchorage Alaska Urgent Care Medical Clinic",
            "link": "https://www.alaskamedicalclinics.com/locations/alaska-urgent-care/",
            "snippet": "We provide complete family medicine and urgent care services seven days a week, ensuring that our patients always have access to high-quality care whenever ...",
            "position": 1
        },
        {
            "title": "Alaska Medical Clinics - Alaska Urgent Care & Wasilla Medical Clinic",
            "link": "https://www.alaskamedicalclinics.com/",
            "snippet": "We provide walk-in acute illness and injury treatment for conditions requiring laceration repair, x-ray, rapid COVID-19 testing, flu and strep testing, and more ...",
            "sitelinks": [
                {
                    "title": "Alaska Urgent Care",
                    "link": "https://www.alaskamedicalclinics.com/locations/alaska-urgent-care/"
                },
                {
                    "title": "Wasilla",
                    "link": "https://www.alaskamedicalclinics.com/locations/wasilla-medical-clinic/"
                },
                {
                    "title": "Urgent Care",
                    "link": "https://www.alaskamedicalclinics.com/services/urgent-care/"
                },
                {
                    "title": "Team",
                    "link": "https://www.alaskamedicalclinics.com/team/"
                }
            ],
            "position": 2
        },
        {
            "title": "Diamond Neighborhoods Family Health Center | Clinic Locations",
            "link": "https://www.fhcsd.org/diamond-neighborhoods-family-health-center/",
            "snippet": "Located at the corner of Market and 47th Streets, Diamond Neighborhoods Family Health Center offers a wide range of health care services.",
            "position": 3
        },
        {
            "title": "Diamond Medical Clinic",
            "link": "https://diamondmedclinic.com/",
            "snippet": "Drop us a line! ... Sign up for our email list for updates, promotions, and more. Send. This site is protected by reCAPTCHA and ...",
            "position": 4
        },
        {
            "title": "Dimond/Jewel Lake - Urgent Care Medical Clinic",
            "link": "https://www.alaskaurgentcaremedicalclinic.com/dimond-jewel-lake",
            "snippet": "Jewel Lake Location. Hours: Mon-Fri: 8:00AM-6:00PM. Sat-Sun: 11:00AM-4:00PM. 9150 Jewel Lake Rd Suite B, Anchorage, AK, 99502 ...",
            "attributes": {
                "Missing": "website | Show results with:website"
            },
            "position": 5
        }
    ],
    "relatedSearches": [
        {
            "query": "Wasilla Medical Clinic"
        },
        {
            "query": "Clinics in anchorage alaska"
        },
        {
            "query": "First Care Medical"
        },
        {
            "query": "Anchorage Urgent Care vet"
        },
        {
            "query": "Alpine Medical Group"
        },
        {
            "query": "Alaska medical solutions wasilla"
        },
        {
            "query": "24 hour Urgent care Anchorage"
        },
        {
            "query": "Diamond urgent care"
        }
    ],
    "credits": 1
}