{
    "searchParameters": {
        "q": "Laramie Internal Medicine address",
        "gl": "us",
        "hl": "en",
        "type": "search",
        "num": 5,
        "engine": "google"
    },
    "answerBox": {
        "title": "Dr. Mythe Laramie, MD / Address",
        "answer": "1515 E Alluvial Ave #101, Fresno, CA 93720"
    },
    "organic": [
        {
            "title": "Ivinson Medical Group",
            "link": "https://www.ivinsonhospital.org/ivinson-medical-group",
            "snippet": "255 N 30th St Laramie, WY 82072 ... It is my belief that Ivinson Memorial Hospital can be the best small hospital in the country. \u2014 Doug Faus, CEO.",
            "position": 1
        },
        {
            "title": "Mythe Laramie, MD - Internal Medicine in Fresno CA - MDVIP",
            "link": "https://www.mdvip.com/doctors/mythelaramiemd",
            "snippet": "Mythe Laramie, MD - Internal Medicine. More about Dr. Laramie call 559.435.0339. Get Started Today. This physician wants to get to know you and your health ...",
            "position": 2
        },
        {
            "title": "Dr. Mythe Laramie, MD: Internal Medicine Doctor - Fresno, CA",
            "link": "https://www.medicalnewstoday.com/provider/dr-mythe-laramie-1801907399",
            "snippet": "Dr. Laramie's office is located at 1515 E Alluvial Ave Ste 101 Fresno, CA 93720. Get a map and directions to Dr. Laramie's office here.",
            "sitelinks": [
                {
                    "title": "Overview",
                    "link": "https://www.medicalnewstoday.com/provider/dr-mythe-laramie-1801907399#:~:text=Overview,-Dr.%20Mythe%20Laramie%2C"
                },
                {
                    "title": "Locations",
                    "link": "https://www.medicalnewstoday.com/provider/dr-mythe-laramie-1801907399#:~:text=Locations,-button"
                },
                {
                    "title": "Ratings & Reviews",
                    "link": "https://www.medicalnewstoday.com/provider/dr-mythe-laramie-1801907399#:~:text=Ratings%20%26%20Reviews"
                }
            ],
            "rating": 4.3,
            "ratingCount": 17,
            "position": 3
        },
        {
            "title": "Primary Care - Ivinson Memorial Hospital",
            "link": "https://www.ivinsonhospital.org/primary-care",
            "snippet": "The Primary Care clinic at Ivinson Medical Group serves adult patients from Laramie and the surrounding areas with a caring team of providers and staff.",
            "position": 4
        },
        {
            "title": "Mythe Laramie, MD | Saint Agnes Medical Center",
            "link": "https://www.samc.com/provider/mythe-laramie-md-internal-medicine",
            "snippet": "Mythe Laramie specializes in Internal Medicine at Medical Office. For an appointment call 559-435-0339.",
            "position": 5
        }
    ],
    "relatedSearches": [
        {
            "query": "primary care doctors in laramie, wy"
        },
        {
            "query": "Ivinson memorial hospital staff directory"
        },
        {
            "query": "Dr Graham Laramie, WY"
        },
        {
            "query": "Doctors in Laramie, Wyoming"
        },
        {
            "query": "Govaerts Laramie"
        },
        {
            "query": "dr. laramie"
        },
        {
            "query": "Dr Jeannine Laramie"
        },
        {
            "query": "Dr Talbot Laramie, WY"
        }
    ],
    "credits": 1
}