{
    "searchParameters": {
        "q": "Multnomah County Aging, Disability, and Veterans Services address",
        "gl": "us",
        "hl": "en",
        "type": "search",
        "num": 5,
        "engine": "google"
    },
    "answerBox": {
        "title": "Multnomah County Aging, Disability and Veterans Services / Address",
        "answer": "5325 NE Martin Luther King Jr Blvd, Portland, OR 97211"
    },
    "organic": [
        {
            "title": "Locations | Multnomah County",
            "link": "https://multco.us/info/locations-0",
            "snippet": "Aging, Disability and Veterans Services Branch Offices ; East Area Office \u00b7 600 NE 8th St, Rm 100. Gresham, OR 97030 \u00b7 (503) 988-3840 \u00b7 (503) 988-5676 ; North/ ...",
            "position": 1
        },
        {
            "title": "Aging, Disability & Veterans Services | Multnomah County",
            "link": "https://multco.us/departments/aging-disability-veterans-services",
            "snippet": "Call the Aging and Disability Resource Connection (ADRC) at 503-988-3646. Get needs assessed, identify services and connect with providers of those services.",
            "position": 2
        },
        {
            "title": "Aging and Disability Resource Connection Helpline",
            "link": "https://multco.us/info/aging-and-disability-resource-connection-helpline",
            "snippet": "To contact the ADRC, call 855-ORE-ADRC (855-673-2372) or 503-988-3646. You can also search the ADRC online database.",
            "position": 3
        },
        {
            "title": "Aging Disability & Veteran Services - Multnomah County ... - FindHelp",
            "link": "https://www.findhelp.org/multnomah-county-department-of-county-human-services-(dchs)--portland-or--aging-disability-&-veteran-services/5140338624430080?postal=97201",
            "snippet": "Hours and Locations Closest to 97201 ; Multnomah County Office. 1.21 miles away - Get Directions. 209 Southwest 4th Avenue Portland, OR 97204 ; Southeast Office.",
            "position": 4
        },
        {
            "title": "MULTNOMAH COUNTY AGING, DISABILITY AND VETERANS ...",
            "link": "https://tenantconnect.org/resources/multnomah-county-aging-disability-and-veterans-services-division/",
            "snippet": "Call the Aging and Disability Resource Connection (ADRC) at 503.988.3646 or email adrc@multco.us(link sends e-mail), for 24-hour information and assistance to ...",
            "position": 5
        }
    ],
    "credits": 1
}