{
    "searchParameters": {
        "q": "Ryan Allen D.O.",
        "gl": "us",
        "hl": "en",
        "type": "maps",
        "engine": "google"
    },
    "ll": "@36.144978,-95.9653068,4z",
    "places": [
        {
            "position": 1,
            "title": "Ryan S Allen DO",
            "address": "2358 S County Trl, East Greenwich, RI 02818",
            "latitude": 41.6325157,
            "longitude": -71.4927794,
            "rating": 5,
            "ratingCount": 1,
            "type": "Internist",
            "types": [
                "Internist",
                "Practitioner service location"
            ],
            "website": "http://www.brennancroninassoc.com/",
            "phoneNumber": "(401) 886-6000",
            "openingHours": {
                "Tuesday": "8\u202fAM\u20135\u202fPM",
                "Wednesday": "8\u202fAM\u20135\u202fPM",
                "Thursday": "8\u202fAM\u20135\u202fPM",
                "Friday": "8\u202fAM\u20135\u202fPM",
                "Saturday": "Closed",
                "Sunday": "Closed",
                "Monday": "8\u202fAM\u20135\u202fPM"
            },
            "thumbnailUrl": "https://streetviewpixels-pa.googleapis.com/v1/thumbnail?panoid=oX6BOryqee_c7TryPE42Tw&cb_client=search.gws-prod.gps&w=80&h=92&yaw=64.773834&pitch=0&thumbfov=100",
            "cid": "5302817149398996020",
            "fid": "0x89e44b87fb3fffff:0x4997641a12c6d434",
            "placeId": "ChIJ__8_-4dL5IkRNNTGEhpkl0k"
        },
        {
            "position": 2,
            "title": "Allen Ryan Do",
            "address": "2342 Professional Pkwy STE 260, Santa Maria, CA 93455",
            "latitude": 34.9180233,
            "longitude": -120.4378342,
            "rating": 3.8,
            "ratingCount": 17,
            "type": "Family practice physician",
            "types": [
                "Family practice physician"
            ],
            "phoneNumber": "(805) 348-3910",
            "openingHours": {
                "Tuesday": "8\u202fAM\u20135\u202fPM",
                "Wednesday": "8\u202fAM\u20135\u202fPM",
                "Thursday": "8\u202fAM\u20135\u202fPM",
                "Friday": "8\u202fAM\u20135\u202fPM",
                "Saturday": "Closed",
                "Sunday": "Closed",
                "Monday": "8\u202fAM\u20135\u202fPM"
            },
            "thumbnailUrl": "https://lh3.googleusercontent.com/gps-cs-s/AB5caB9njBa1Cz1ZIJ3CTPsSozpV9eSDAHe9bAd6UGHgoTxiguIkSqZ16LEV7ayGVYQXopXRFrG1gaps-9PdpSybJnT-UKkbeRsjLgqjOjU67Eb5l0utShvrI0yrC07PUgAuG1z1BjRCpA",
            "cid": "12092867210671052928",
            "fid": "0x80ec6b57b1c9d827:0xa7d27ea848045880",
            "placeId": "ChIJJ9jJsVdr7IARgFgESKh-0qc"
        },
        {
            "position": 3,
            "title": "Ryan W. Allen, DO",
            "address": "975 Chambers St, South Ogden, UT 84403",
            "latitude": 41.164483399999995,
            "longitude": -111.9533204,
            "rating": 4.5,
            "ratingCount": 11,
            "type": "Family practice physician",
            "types": [
                "Family practice physician"
            ],
            "website": "https://doctors.intermountainhealth.org/provider/Ryan%20W%20Allen/2556748",
            "phoneNumber": "(801) 387-6200",
            "bookingLinks": [
                "https://doctors.intermountainhealth.org/book/2556748?utm_source=reserve_with_google&rwg_token=AAiGsoaevD-XWwQmeDf014sLZDPINJm_Qo3m7JMjiXWS4VD_xkrY1wxB1wo1doVgKXUCIjmHJbc95D65Ihhp_yL4JW9VoNoezIANJFL-M2QMUAl5Voulx-4%3D"
            ],
            "thumbnailUrl": "https://streetviewpixels-pa.googleapis.com/v1/thumbnail?panoid=aWNahlXEncNEe8cxEnr3tw&cb_client=search.gws-prod.gps&w=80&h=92&yaw=257.5552&pitch=0&thumbfov=100",
            "cid": "737840432864166010",
            "fid": "0x8753051d149fec49:0xa3d55f6e5ca007a",
            "placeId": "ChIJSeyfFB0FU4cRegDK5fZVPQo"
        },
        {
            "position": 4,
            "title": "Ryan Allen, DO",
            "address": "105 Ranch to Market Rd 2342, Kingsland, TX 78639",
            "latitude": 30.6574404,
            "longitude": -98.4246933,
            "rating": 5,
            "ratingCount": 1,
            "type": "Family practice physician",
            "types": [
                "Family practice physician"
            ],
            "website": "https://www.bswhealth.com/physician/ryan-allen?utm_source=pg-google&utm_medium=organic&utm_campaign=pg-listings",
            "phoneNumber": "(325) 388-9400",
            "openingHours": {
                "Tuesday": "8\u202fAM\u20135\u202fPM",
                "Wednesday": "8\u202fAM\u20135\u202fPM",
                "Thursday": "8\u202fAM\u20135\u202fPM",
                "Friday": "8\u202fAM\u20135\u202fPM",
                "Saturday": "Closed",
                "Sunday": "Closed",
                "Monday": "8\u202fAM\u20135\u202fPM"
            },
            "bookingLinks": [
                "https://www.bswhealth.com/physician/ryan-allen?utm_source=google-mybusiness&utm_medium=organic&utm_campaign=1407206527-9531&utm_content=-make-appointment"
            ],
            "thumbnailUrl": "https://lh3.googleusercontent.com/p/AF1QipOStOUwA9MpzvtpMOg1VXlpz68-rTKsVCMUzjiu",
            "cid": "1281738674933310431",
            "fid": "0x865aff6eb032035f:0x11c9a688ae47a3df",
            "placeId": "ChIJXwMysG7_WoYR36NHroimyRE"
        }
    ],
    "credits": 3
}