{
    "searchParameters": {
        "q": "Creekside Surgery Center address",
        "gl": "us",
        "hl": "en",
        "type": "search",
        "num": 5,
        "engine": "google"
    },
    "organic": [
        {
            "title": "Creekside Surgery Center \u2013 Serving Anchorage and all of Alaska for ...",
            "link": "https://www.creeksideasc.com/",
            "snippet": "Creekside Surgery Center. Serving Anchorage and all of Alaska for your Orthopedic, Ear Nose & Throat, Podiatry and Pain Management needs.",
            "sitelinks": [
                {
                    "title": "Contact Us",
                    "link": "https://www.creeksideasc.com/contact-us/"
                },
                {
                    "title": "Physicians",
                    "link": "https://www.creeksideasc.com/physicians/"
                },
                {
                    "title": "Employment",
                    "link": "https://www.creeksideasc.com/employment/"
                },
                {
                    "title": "Preparing for Your Surgery",
                    "link": "https://www.creeksideasc.com/patient-information/preparing-for-your-surgery/"
                }
            ],
            "position": 1
        },
        {
            "title": "Contact Us - Creekside Surgery Center",
            "link": "https://www.creeksideasc.com/contact-us/",
            "snippet": "Creekside Surgery Center. 3831 Piper Street Suite S-110. Anchorage, Alaska 99508. Phone (907) 339-7800. Fax (907) 339-7890. Map & Directions.",
            "position": 2
        },
        {
            "title": "Creekside Surgery Center - Providence Directory",
            "link": "http://phppd.providence.org/Intel/Facility/View/560707994884335?PlanName=",
            "snippet": "Creekside Surgery Center. 3831 Piper St, Anchorage, AK 99508. Phone 907 ... This is the street address and phone number of the hospital. The information ...",
            "position": 3
        },
        {
            "title": "Creekside | Mountain View Hospital",
            "link": "https://www.mountainviewhospital.org/services/surgery/creekside/",
            "snippet": "Phone: (208) 557-2767 Address:2375 E Sunnyside Rd, Idaho Falls, ID 83404 ... Creekside has two operating suites. Home \u00b7 Services \u00b7 Surgery; Creekside. Mountain ...",
            "position": 4
        },
        {
            "title": "Physicians - Anchorage - Creekside Surgery Center",
            "link": "https://www.creeksideasc.com/physicians/",
            "snippet": "If you have any questions or concerns about physician ownership in this facility, please ask to speak with the Administrator.",
            "position": 5
        }
    ],
    "places": [
        {
            "title": "Creekside Surgery Center",
            "address": "Anchorage, AK",
            "rating": 4.5,
            "ratingCount": 18,
            "cid": "10014340471235935411"
        },
        {
            "title": "Creekside Outpatient Surgery Center",
            "address": "Idaho Falls, ID",
            "rating": 3.4,
            "ratingCount": 16,
            "cid": "12657084662333340567"
        }
    ],
    "relatedSearches": [
        {
            "query": "Creekside Surgery Center jobs"
        },
        {
            "query": "Creekside Surgery Center billing"
        },
        {
            "query": "Providence Surgery Center"
        },
        {
            "query": "Providence Surgery Center Anchorage, AK"
        },
        {
            "query": "Providence Creekside"
        }
    ],
    "credits": 1
}