{
    "searchParameters": {
        "q": "Hematology Oncology Assoc.",
        "gl": "us",
        "hl": "en",
        "type": "maps",
        "engine": "google"
    },
    "ll": "@34.7292881,-97.5535103,4z",
    "places": [
        {
            "position": 1,
            "title": "Hematology-Oncology Associates Of CNY - East Syracuse",
            "address": "5008 Brittonfield Pkwy, East Syracuse, NY 13057",
            "latitude": 43.1027616,
            "longitude": -76.054619,
            "rating": 4.4,
            "ratingCount": 129,
            "type": "Cancer treatment center",
            "types": [
                "Cancer treatment center",
                "Hematologist"
            ],
            "website": "https://www.hoacny.com/contact/brittonfield-east-syracuse-ny?utm_source=google&utm_medium=local-listings",
            "phoneNumber": "(315) 472-7504",
            "openingHours": {
                "Tuesday": "7\u202fAM\u20135\u202fPM",
                "Wednesday": "7\u202fAM\u20135\u202fPM",
                "Thursday": "7\u202fAM\u20135\u202fPM",
                "Friday": "7\u202fAM\u20135\u202fPM",
                "Saturday": "Closed",
                "Sunday": "Closed",
                "Monday": "7\u202fAM\u20135\u202fPM"
            },
            "thumbnailUrl": "https://lh3.googleusercontent.com/p/AF1QipN7-w_6Z-SxcFXkaKmpXmoor1UsNHl8Jcp7tFkv",
            "cid": "1766716491757791353",
            "fid": "0x89d99293dc197055:0x1884a349ee0c2879",
            "placeId": "ChIJVXAZ3JOS2YkReSgM7kmjhBg"
        },
        {
            "position": 2,
            "title": "Hematology Oncology Associates of Fredericksburg - The Pines",
            "address": "4545 Empire Ct, Fredericksburg, VA 22408",
            "latitude": 38.2511047,
            "longitude": -77.4921545,
            "rating": 4.8,
            "ratingCount": 655,
            "type": "Oncologist",
            "types": [
                "Oncologist"
            ],
            "website": "https://hoafredericksburg.com/",
            "phoneNumber": "(540) 371-0079",
            "openingHours": {
                "Tuesday": "7:45\u202fAM\u20136\u202fPM",
                "Wednesday": "7:45\u202fAM\u20136\u202fPM",
                "Thursday": "7:45\u202fAM\u20136\u202fPM",
                "Friday": "7:45\u202fAM\u20136\u202fPM",
                "Saturday": "Closed",
                "Sunday": "Closed",
                "Monday": "7:45\u202fAM\u20136\u202fPM"
            },
            "bookingLinks": [
                "https://hoafredericksburg.com/request-an-appointment/"
            ],
            "thumbnailUrl": "https://lh3.googleusercontent.com/p/AF1QipP3CaR51Zb6TruX4K3v2RB3QSGPhGQvjCEWYLgg",
            "cid": "11472462358161673769",
            "fid": "0x89b6c140e43bc1f1:0x9f365fbb25444e29",
            "placeId": "ChIJ8cE75EDBtokRKU5EJbtfNp8"
        },
        {
            "position": 3,
            "title": "Hematology Oncology Associates of Brooklyn",
            "address": "1660 E 14th St #401, Brooklyn, NY 11229",
            "latitude": 40.608824399999996,
            "longitude": -73.9595636,
            "rating": 3.4,
            "ratingCount": 16,
            "type": "Medical clinic",
            "types": [
                "Medical clinic"
            ],
            "website": "http://www.brooklynoncology.com/",
            "phoneNumber": "(646) 883-0385",
            "openingHours": {
                "Tuesday": "9\u202fAM\u20135\u202fPM",
                "Wednesday": "9\u202fAM\u20135\u202fPM",
                "Thursday": "9\u202fAM\u20135\u202fPM",
                "Friday": "9\u202fAM\u20133\u202fPM",
                "Saturday": "Closed",
                "Sunday": "Closed",
                "Monday": "9\u202fAM\u20135\u202fPM"
            },
            "thumbnailUrl": "https://lh3.googleusercontent.com/gps-cs-s/AB5caB8X0lZJj9VP9muBQzvxPh4Pp5Hp4sYkRPJtGbkuL4hVQozKiInHF7H7PL6Ha_uOCCqkwZGfzSX387JMopuMttZw88hU5uDdr3Wb7C6phDxl7NpU7Gc26l5YAcPwBM9MRJr1JSgVUw",
            "cid": "9581871962038158689",
            "fid": "0x89c244eb52d215ad:0x84f9a5c8548f4561",
            "placeId": "ChIJrRXSUutEwokRYUWPVMil-YQ"
        },
        {
            "position": 4,
            "title": "Hematology & Oncology Associates of Alabama - HOAA",
            "address": "Brookwood Medical Plaza, 513 Brookwood Blvd #275, Birmingham, AL 35209",
            "latitude": 33.465871,
            "longitude": -86.77660399999999,
            "rating": 4.9,
            "ratingCount": 778,
            "type": "Medical clinic",
            "types": [
                "Medical clinic",
                "Cancer treatment center",
                "Hematologist",
                "Oncologist",
                "Pharmacy"
            ],
            "website": "http://www.hoaallc.com/",
            "phoneNumber": "(205) 502-4700",
            "openingHours": {
                "Tuesday": "8\u202fAM\u20135\u202fPM",
                "Wednesday": "8\u202fAM\u20135\u202fPM",
                "Thursday": "8\u202fAM\u20135\u202fPM",
                "Friday": "8\u202fAM\u20135\u202fPM",
                "Saturday": "Closed",
                "Sunday": "Closed",
                "Monday": "8\u202fAM\u20135\u202fPM"
            },
            "thumbnailUrl": "https://lh3.googleusercontent.com/p/AF1QipMEfMl62xEwX8pczOJUQIragSxW6ds2u3TxBqhZ",
            "cid": "12754471703444393957",
            "fid": "0x88891998cdb0ba89:0xb100fc702d930fe5",
            "placeId": "ChIJibqwzZgZiYgR5Q-TLXD8ALE"
        },
        {
            "position": 5,
            "title": "Hematology/Oncology Associates",
            "address": "2600 Kings Hwy #340, Shreveport, LA 71103",
            "latitude": 32.481406,
            "longitude": -93.779331,
            "rating": 4.9,
            "ratingCount": 431,
            "type": "Cancer treatment center",
            "types": [
                "Cancer treatment center",
                "Hematologist",
                "Oncologist"
            ],
            "website": "http://www.wkhs.com/Cancer/Physicians/Hematology-Oncology",
            "phoneNumber": "(318) 212-8620",
            "openingHours": {
                "Tuesday": "8\u202fAM\u20135\u202fPM",
                "Wednesday": "8\u202fAM\u20135\u202fPM",
                "Thursday": "8\u202fAM\u20135\u202fPM",
                "Friday": "8\u202fAM\u20135\u202fPM",
                "Saturday": "Closed",
                "Sunday": "Closed",
                "Monday": "8\u202fAM\u20135\u202fPM"
            },
            "thumbnailUrl": "https://lh3.googleusercontent.com/gps-cs-s/AB5caB8c1nlRX00JzmlVGVKl4A8hCkqc6piJwS_7cgVsq5uvazw3nM_KrhqH2mpuKGztObFXhUO-X2qDUg5K-tGfoIalHKjEtAlbV3UQXVNW5lJxTXL8QXlNhCfB1uNhQx8sUP6DsT8T",
            "cid": "15998063379680873836",
            "fid": "0x8636cd7e061a131b:0xde0489e1e8104d6c",
            "placeId": "ChIJGxMaBn7NNoYRbE0Q6OGJBN4"
        },
        {
            "position": 6,
            "title": "Hematology Oncology Associates of Boca Raton - part of the GenesisCare Network",
            "address": "9970 S Central Park Blvd N, Boca Raton, FL 33428",
            "latitude": 26.3558146,
            "longitude": -80.20221509999999,
            "rating": 4.6,
            "ratingCount": 18,
            "type": "Cancer treatment center",
            "types": [
                "Cancer treatment center"
            ],
            "website": "https://www.genesiscareus.com/en/our-locations/boca-raton-h03?utm_source=google&utm_medium=organic&utm_campaign=gmb_listings&utm_term=button&utm_content=visit_website",
            "phoneNumber": "(561) 482-6611",
            "openingHours": {
                "Tuesday": "8\u202fAM\u20135\u202fPM",
                "Wednesday": "8\u202fAM\u20135\u202fPM",
                "Thursday": "8\u202fAM\u20135\u202fPM",
                "Friday": "8\u202fAM\u20135\u202fPM",
                "Saturday": "Closed",
                "Sunday": "Closed",
                "Monday": "8\u202fAM\u20135\u202fPM"
            },
            "thumbnailUrl": "https://streetviewpixels-pa.googleapis.com/v1/thumbnail?panoid=hvDFRAlpNs2GD-V2ieP97w&cb_client=search.gws-prod.gps&w=80&h=92&yaw=275.2329&pitch=0&thumbfov=100",
            "cid": "11530572391288825415",
            "fid": "0x88d91be44b4b3323:0xa004d27f8fb26647",
            "placeId": "ChIJIzNLS-Qb2YgRR2ayj3_SBKA"
        },
        {
            "position": 7,
            "title": "Hematology-Oncology Associates of the Treasure Coast",
            "address": "2081 SE Ocean Blvd STE 2A, Stuart, FL 34996",
            "latitude": 27.197856899999998,
            "longitude": -80.2245559,
            "rating": 4,
            "ratingCount": 8,
            "type": "Medical clinic",
            "types": [
                "Medical clinic",
                "Cancer treatment center",
                "Internist"
            ],
            "website": "http://www.hemoncfl.com/",
            "phoneNumber": "(772) 223-5982",
            "thumbnailUrl": "https://streetviewpixels-pa.googleapis.com/v1/thumbnail?panoid=PfVVQbAd4Y48WTLk2udqig&cb_client=search.gws-prod.gps&w=80&h=92&yaw=11.682685&pitch=0&thumbfov=100",
            "cid": "13131764087300070640",
            "fid": "0x88dedd651574da8f:0xb63d65dcc1c09cf0",
            "placeId": "ChIJj9p0FWXd3ogR8JzAwdxlPbY"
        },
        {
            "position": 8,
            "title": "Hematology Oncology Associates of Fredericksburg",
            "address": "125 Woodstream Blvd, Stafford, VA 22556",
            "latitude": 38.474742899999995,
            "longitude": -77.411169,
            "rating": 4.1,
            "ratingCount": 22,
            "type": "Cancer treatment center",
            "types": [
                "Cancer treatment center"
            ],
            "website": "http://www.hoafredericksburg.com/",
            "phoneNumber": "(540) 371-0079",
            "openingHours": {
                "Tuesday": "8\u202fAM\u20135\u202fPM",
                "Wednesday": "8\u202fAM\u20135\u202fPM",
                "Thursday": "8\u202fAM\u20135\u202fPM",
                "Friday": "8\u202fAM\u20132:30\u202fPM",
                "Saturday": "Closed",
                "Sunday": "Closed",
                "Monday": "8\u202fAM\u20135\u202fPM"
            },
            "thumbnailUrl": "https://lh3.googleusercontent.com/gps-cs-s/AB5caB_Qzm10im4UxWFnG86zSPdDaRySMc05epDlAsxlyeftn8XQ_11TI58FDrSMF1nheb77mbK5jY2iKkRVrMCWuy9B372e4DAO0H9Xzi7Ic18nG0yuZREyVU52Yn2mSWiGunX7v3V1",
            "cid": "3344146653650977584",
            "fid": "0x89b6f167310eb01b:0x2e68cba9d7ad8330",
            "placeId": "ChIJG7AOMWfxtokRMIOt16nLaC4"
        },
        {
            "position": 9,
            "title": "Hematology-Oncology Associates of CNY - Camillus",
            "address": "5490 Cobbler Way, Camillus, NY 13031",
            "latitude": 43.035686999999996,
            "longitude": -76.332842,
            "rating": 5,
            "ratingCount": 1,
            "type": "Cancer treatment center",
            "types": [
                "Cancer treatment center",
                "Hematologist",
                "Nutritionist",
                "Oncologist",
                "Radiotherapist",
                "Social worker"
            ],
            "website": "https://www.hoacny.com/contact/new-clinic-wellness-camillus-ny?utm_source=google&utm_medium=local-listings",
            "phoneNumber": "(315) 472-7504",
            "openingHours": {
                "Tuesday": "8\u202fAM\u20135\u202fPM",
                "Wednesday": "8\u202fAM\u20135\u202fPM",
                "Thursday": "8\u202fAM\u20135\u202fPM",
                "Friday": "8\u202fAM\u20135\u202fPM",
                "Saturday": "Closed",
                "Sunday": "Closed",
                "Monday": "8\u202fAM\u20135\u202fPM"
            },
            "thumbnailUrl": "https://lh3.googleusercontent.com/p/AF1QipNTha2sNUBE5_GR7MEWQ3UrLRR_kMpR5zo-E7yI",
            "cid": "8384630692221322082",
            "fid": "0x89d9fa1fff43c561:0x745c3130deb08362",
            "placeId": "ChIJYcVD_x_62YkRYoOw3jAxXHQ"
        },
        {
            "position": 10,
            "title": "Hematology-Oncology Associates Of CNY",
            "address": "37 W Garden St #301, Auburn, NY 13021",
            "latitude": 42.9344989,
            "longitude": -76.5683619,
            "rating": 5,
            "ratingCount": 2,
            "type": "Cancer treatment center",
            "types": [
                "Cancer treatment center",
                "Hematologist"
            ],
            "website": "https://www.hoacny.com/",
            "phoneNumber": "(315) 472-7504",
            "openingHours": {
                "Tuesday": "8\u202fAM\u20135\u202fPM",
                "Wednesday": "8\u202fAM\u20135\u202fPM",
                "Thursday": "8\u202fAM\u20135\u202fPM",
                "Friday": "8\u202fAM\u20135\u202fPM",
                "Saturday": "Closed",
                "Sunday": "Closed",
                "Monday": "8\u202fAM\u20135\u202fPM"
            },
            "thumbnailUrl": "https://lh3.googleusercontent.com/p/AF1QipMcQ4sgpAjMPTfrLIayobDOFz-FgtGUf4OuOtwg",
            "cid": "4642346827659788236",
            "fid": "0x89d0ac168eb56fa1:0x406cedd7f2d2bfcc",
            "placeId": "ChIJoW-1jhas0IkRzL_S8tftbEA"
        },
        {
            "position": 11,
            "title": "Columbus Oncology and Hematology Associates",
            "address": "810 Jasonway Ave a, Columbus, OH 43214",
            "latitude": 40.0598167,
            "longitude": -83.0406915,
            "rating": 4.9,
            "ratingCount": 451,
            "type": "Oncologist",
            "types": [
                "Oncologist",
                "Cancer treatment center",
                "Hematologist",
                "Holistic medicine practitioner",
                "Medical clinic"
            ],
            "website": "https://www.oncologycolumbusohio.com/",
            "phoneNumber": "(614) 442-3130",
            "openingHours": {
                "Tuesday": "8\u202fAM\u20135\u202fPM",
                "Wednesday": "8\u202fAM\u20135\u202fPM",
                "Thursday": "8\u202fAM\u20135\u202fPM",
                "Friday": "8\u202fAM\u20135\u202fPM",
                "Saturday": "Closed",
                "Sunday": "Closed",
                "Monday": "8\u202fAM\u20135\u202fPM"
            },
            "thumbnailUrl": "https://lh3.googleusercontent.com/p/AF1QipP7pJLny4GcgQgV1KQWhMkFihZ7E4gF3Rmx8MwU",
            "cid": "3521025168842128497",
            "fid": "0x88388d00a4d70185:0x30dd31bc620b7c71",
            "placeId": "ChIJhQHXpACNOIgRcXwLYrwx3TA"
        },
        {
            "position": 12,
            "title": "Louisiana Hematology & Oncology Associates",
            "address": "4950 Essen Ln #500, Baton Rouge, LA 70809",
            "latitude": 30.403783299999997,
            "longitude": -91.1047803,
            "rating": 4.1,
            "ratingCount": 13,
            "type": "Cancer treatment center",
            "types": [
                "Cancer treatment center"
            ],
            "website": "https://www.brgeneral.org/locations/louisiana-hematology-oncology-associates/",
            "phoneNumber": "(225) 767-1311",
            "openingHours": {
                "Tuesday": "8\u202fAM\u20135\u202fPM",
                "Wednesday": "8\u202fAM\u20135\u202fPM",
                "Thursday": "8\u202fAM\u20135\u202fPM",
                "Friday": "8\u202fAM\u20135\u202fPM",
                "Saturday": "Closed",
                "Sunday": "Closed",
                "Monday": "8\u202fAM\u20135\u202fPM"
            },
            "thumbnailUrl": "https://lh3.googleusercontent.com/p/AF1QipPGV4ZejqqRIQ_FEJwItETYYh8wC_FJPi_6P6Ab",
            "cid": "1177560601209805870",
            "fid": "0x8626a45c9c9c4431:0x10578920b89b1c2e",
            "placeId": "ChIJMUScnFykJoYRLhybuCCJVxA"
        },
        {
            "position": 13,
            "title": "Hematology Oncology Associates",
            "address": "715 Dr Martin Luther King Jr Ave NE #102, Albuquerque, NM 87102",
            "latitude": 35.085864099999995,
            "longitude": -106.63867049999999,
            "rating": 4.2,
            "ratingCount": 5,
            "type": "Medical clinic",
            "types": [
                "Medical clinic",
                "Doctor"
            ],
            "phoneNumber": "(505) 727-3040",
            "openingHours": {
                "Tuesday": "8\u202fAM\u20135\u202fPM",
                "Wednesday": "8\u202fAM\u20135\u202fPM",
                "Thursday": "8\u202fAM\u20135\u202fPM",
                "Friday": "8\u202fAM\u20135\u202fPM",
                "Saturday": "Closed",
                "Sunday": "Closed",
                "Monday": "8\u202fAM\u20135\u202fPM"
            },
            "thumbnailUrl": "https://streetviewpixels-pa.googleapis.com/v1/thumbnail?panoid=9xBZJXvDXmK6RXfMc2v_Dw&cb_client=search.gws-prod.gps&w=80&h=92&yaw=244.44601&pitch=0&thumbfov=100",
            "cid": "11486965205141958642",
            "fid": "0x87220c98e82648b1:0x9f69e5fe57c22ff2",
            "placeId": "ChIJsUgm6JgMIocR8i_CV_7laZ8"
        },
        {
            "position": 14,
            "title": "Hematology Oncology Associates",
            "address": "925 Gessner Rd Suite 310, Houston, TX 77024",
            "latitude": 29.7817533,
            "longitude": -95.54465119999999,
            "rating": 3,
            "ratingCount": 2,
            "type": "Medical clinic",
            "types": [
                "Medical clinic",
                "Hematologist"
            ],
            "phoneNumber": "(713) 467-1630",
            "thumbnailUrl": "https://streetviewpixels-pa.googleapis.com/v1/thumbnail?panoid=1Yp6GiUzf588YPCl8OvlQg&cb_client=search.gws-prod.gps&w=80&h=92&yaw=355.9624&pitch=0&thumbfov=100",
            "cid": "13099936840645419774",
            "fid": "0x8640c4bc4235c985:0xb5cc53266eb922fe",
            "placeId": "ChIJhck1QrzEQIYR_iK5biZTzLU"
        },
        {
            "position": 15,
            "title": "Hematology and Oncology Associates of Northern California",
            "address": "1631 Creekside Dr #102, Folsom, CA 95630",
            "latitude": 38.671414999999996,
            "longitude": -121.1474571,
            "rating": 4.4,
            "ratingCount": 15,
            "type": "Oncologist",
            "types": [
                "Oncologist",
                "Hematologist"
            ],
            "website": "https://www.hoaonc.com/",
            "phoneNumber": "(916) 250-0377",
            "openingHours": {
                "Tuesday": "8\u202fAM\u20135\u202fPM",
                "Wednesday": "8\u202fAM\u20135\u202fPM",
                "Thursday": "8\u202fAM\u20135\u202fPM",
                "Friday": "8\u202fAM\u20133:30\u202fPM",
                "Saturday": "Closed",
                "Sunday": "Closed",
                "Monday": "8\u202fAM\u20135\u202fPM"
            },
            "thumbnailUrl": "https://lh3.googleusercontent.com/p/AF1QipMR0swgm6BKJCRgTQsK1aTsi9ihN7Qk6VNomKZ6",
            "cid": "13508222498532258642",
            "fid": "0x809ae55247882871:0xbb76d8caf3f47352",
            "placeId": "ChIJcSiIR1LlmoARUnP088rYdrs"
        },
        {
            "position": 16,
            "title": "Louisiana Hematology Oncology Associates at Baton Rouge General",
            "address": "8585 Picardy Ave Suite 410 Entrance 2, Baton Rouge, LA 70809",
            "latitude": 30.392697599999998,
            "longitude": -91.09520069999999,
            "type": "Cancer treatment center",
            "types": [
                "Cancer treatment center",
                "Hematologist",
                "Oncologist"
            ],
            "website": "https://www.brgeneral.org/location/louisiana-hematology-oncology-associates",
            "phoneNumber": "(225) 215-0800",
            "openingHours": {
                "Tuesday": "8\u202fAM\u20134:30\u202fPM",
                "Wednesday": "8\u202fAM\u20134:30\u202fPM",
                "Thursday": "8\u202fAM\u20134:30\u202fPM",
                "Friday": "Closed",
                "Saturday": "Closed",
                "Sunday": "Closed",
                "Monday": "8\u202fAM\u20134:30\u202fPM"
            },
            "bookingLinks": [
                "https://www.brgeneral.org/locations/louisiana-hematology-oncology-associates/"
            ],
            "thumbnailUrl": "https://lh3.googleusercontent.com/p/AF1QipMjPiZkWnqmmYtb2y0xAac6nDUrGij96e0ViDzT",
            "cid": "8114520404783846435",
            "fid": "0x8626a5d741afda83:0x709c9150c9ccd423",
            "placeId": "ChIJg9qvQdelJoYRI9TMyVCRnHA"
        }
    ],
    "credits": 3
}