{
    "searchParameters": {
        "q": "UNM Cancer Research & Treatment Center address",
        "gl": "us",
        "hl": "en",
        "type": "search",
        "num": 5,
        "engine": "google"
    },
    "organic": [
        {
            "title": "Find Us | Contact Us | Maps | Directions | UNM Cancer Center",
            "link": "https://unmhealth.org/cancer/appointments/find-us.html",
            "snippet": "The University of New Mexico Comprehensive Cancer Center 1201 Camino de Salud NE, Albuquerque, New Mexico 87102 (View on Google maps)",
            "sitelinks": [
                {
                    "title": "Maps & Directions",
                    "link": "https://unmhealth.org/cancer/appointments/find-us.html#:~:text=Maps%20%26%20Directions"
                },
                {
                    "title": "Unm Comprehensive",
                    "link": "https://unmhealth.org/cancer/appointments/find-us.html#:~:text=.-,UNM%20Comprehensive"
                },
                {
                    "title": "Contact Us",
                    "link": "https://unmhealth.org/cancer/appointments/find-us.html#:~:text=Contact%20Us,-Clinic%20Numbers"
                }
            ],
            "position": 1
        },
        {
            "title": "UNM Comprehensive Cancer Center | Albuquerque, New Mexico",
            "link": "https://unmhealth.org/locations/cancer-center.html",
            "snippet": "Call to make an appointment. 505-272-4946. ... To navigate, press the arrow keys. ... 2055 Pacheco St. Santa Fe, NM 87144.",
            "sitelinks": [
                {
                    "title": "Albuquerque Location",
                    "link": "https://unmhealth.org/locations/cancer-center.html#:~:text=Albuquerque%20Location"
                },
                {
                    "title": "Santa Fe Location",
                    "link": "https://unmhealth.org/locations/cancer-center.html#:~:text=Santa%20Fe%20Location"
                },
                {
                    "title": "Cancer Specialties And...",
                    "link": "https://unmhealth.org/locations/cancer-center.html#:~:text=Cancer%20Specialties%20and%20Programs"
                }
            ],
            "position": 2
        },
        {
            "title": "University of New Mexico Cancer Research & Treatment Center",
            "link": "https://cancercenters.cancer.gov/cancer-centers/university-new-mexico-cancer-research-treatment-center",
            "snippet": "The facility has 17 clinic and service lines, including New Mexico's only bone marrow and stem cell transplant program, which offers autologous and allogeneic ...",
            "position": 3
        },
        {
            "title": "University of New Mexico Cancer Research Building - Wikipedia",
            "link": "https://en.wikipedia.org/wiki/University_of_New_Mexico_Cancer_Research_Building",
            "snippet": "UNM Cancer Center, 1201 Camino de Salud NE 1, University of New Mexico, Albuquerque, NM 87102.",
            "position": 4
        },
        {
            "title": "UNM CANCER CENTER - Updated April 2025 - 10 Reviews - Yelp",
            "link": "https://www.yelp.com/biz/unm-cancer-center-albuquerque",
            "snippet": "1201 Camino De Salud NE. Albuquerque, NM 87102. Midtown/University ; (505) 272-4946 ; Visit Website. http://cancer.unm.edu ; More Info. Hours ...",
            "rating": 3,
            "ratingCount": 10,
            "position": 5
        }
    ],
    "places": [
        {
            "title": "UNM Comprehensive Cancer Center",
            "address": "Albuquerque, NM",
            "rating": 3.6,
            "ratingCount": 70,
            "cid": "17444617878087057336"
        },
        {
            "title": "UNM Cancer Research Facility",
            "address": "Albuquerque, NM",
            "rating": 5,
            "ratingCount": 7,
            "cid": "5717172553676776701"
        }
    ],
    "relatedSearches": [
        {
            "query": "1201 Camino de Salud NE albuquerque NM 87102"
        },
        {
            "query": "Cancer Center Albuquerque NM"
        },
        {
            "query": "UNM Cancer Center address"
        },
        {
            "query": "Best cancer Hospital in New Mexico"
        },
        {
            "query": "UNM Cancer Center doctors"
        },
        {
            "query": "UNM Cancer Center Directory"
        },
        {
            "query": "UNM cancer Center phone number"
        },
        {
            "query": "UNM Cancer Research Facility"
        }
    ],
    "credits": 1
}