{
    "searchParameters": {
        "q": "Taylor Lara, MD website",
        "gl": "us",
        "hl": "en",
        "type": "search",
        "num": 5,
        "engine": "google"
    },
    "organic": [
        {
            "title": "Taylor Lara, MD - Saint Alphonsus",
            "link": "https://www.saintalphonsus.org/provider/taylor-lara",
            "snippet": "Watch Dr. Lara's seminar about Hip and Knee Joint pain. Specific topics included: causes of joint pain, tips for managing joint pain, and modern techniques for ...",
            "rating": 4.8,
            "ratingCount": 121,
            "position": 1
        },
        {
            "title": "Taylor Lara, MD | Trinity Health System",
            "link": "https://saintalphonsushealthalliance.org/provider/taylor-rhodes-lara-md-orthopedic-surgery",
            "snippet": "Taylor Lara, MD \u00b7 Orthopaedic Surgery, Orthopedic Surgery \u00b7 (208) 302-3500 \u00b7 Appointments (New Patients Welcome) \u00b7 Primary Contact.",
            "position": 2
        },
        {
            "title": "Dr. Taylor R. Lara, MD | Boise, ID | Orthopedist | US News Doctors",
            "link": "https://health.usnews.com/doctors/taylor-lara-1870992",
            "snippet": "Dr. Taylor R. Lara has expertise in treating knee replacement, hip replacement, arthritis, among other conditions - see all areas of expertise.",
            "position": 3
        },
        {
            "title": "Dr. Taylor Lara, MD - Orthopedic Surgeon in Boise, ID | Healthgrades",
            "link": "https://www.healthgrades.com/physician/dr-taylor-lara-xylgdrx",
            "snippet": "Taylor Lara, MD is an orthopedic surgeon in Boise, ID and has over 5 years of experience in the medical field. He graduated from University of Tennessee College ...",
            "rating": 4.2,
            "ratingCount": 5,
            "position": 4
        },
        {
            "title": "Watch and Learn About Hip and Knee Joint Pain",
            "link": "https://www.saintalphonsus.org/blog/blogs/wellness/hip-and-knee-joint-pain-seminar",
            "snippet": "Learn about modern techniques and solutions to treat hip joint pain and knee joint pain. Get expert advice from Dr. Lara and Dr. Vaux on ...",
            "date": "Mar 13, 2023",
            "position": 5
        }
    ],
    "images": [
        {
            "title": "Dr. Taylor Lara",
            "imageUrl": "https://www.saintalphonsus.org/sites/default/files/hg_features/hg_provider/9d559ca696494f6a2569ea88566fc8a1.jpg",
            "link": "https://www.saintalphonsus.org/provider/taylor-lara"
        },
        {
            "title": "Dr. Taylor Lara, MD | knee, hip, surgeon | We are proud to welcome ...",
            "imageUrl": "https://lookaside.fbsbx.com/lookaside/crawler/media/?media_id=461809268860976&get_thumbnail=1",
            "link": "https://www.facebook.com/SaintAlphonsus/videos/dr-taylor-lara-md/461809268860976/"
        },
        {
            "title": "Dr Taylor Lara - YouTube",
            "imageUrl": "https://i.ytimg.com/vi/nXjCXCX9zWE/maxresdefault.jpg",
            "link": "https://www.youtube.com/watch?v=nXjCXCX9zWE"
        },
        {
            "title": "Lara Taylor, FNP | Family Medicine | St. Louis, MO | Mercy",
            "imageUrl": "https://www.mercy.net/content/dam/mercy/en/images/doctors/1255924809-h.jpg",
            "link": "https://www.mercy.net/doctor/lara-taylor-fnp/"
        },
        {
            "title": "Taylor Lara, MD | Trinity Health System",
            "imageUrl": "https://saintalphonsushealthalliance.org/sites/default/files/hg-features/hg-providers/default-male.jpg",
            "link": "https://saintalphonsushealthalliance.org/provider/taylor-rhodes-lara-md-orthopedic-surgery"
        },
        {
            "title": "Dr. Taylor Lara",
            "imageUrl": "https://img.youtube.com/vi/nXjCXCX9zWE/hqdefault.jpg",
            "link": "https://www.saintalphonsus.org/provider/taylor-lara"
        },
        {
            "title": "Idaho Today: Dr. Taylor Lara discusses joint pain treatment ...",
            "imageUrl": "https://media.ktvb.com/assets/KTVB/images/0d8021b5-2975-468e-b864-244230955bb1/0d8021b5-2975-468e-b864-244230955bb1_1920x1080.jpg",
            "link": "https://www.ktvb.com/video/news/local/idaho-today/idaho-today-dr-taylor-lara-discusses-joint-pain-treatment-options/277-c34e4e19-5e94-4701-8489-6423d81f7e35"
        },
        {
            "title": "Lara Taylor, FNP | Family Medicine | St. Louis, MO | Mercy",
            "imageUrl": "https://cf-images.us-east-1.prod.boltdns.net/v1/static/830934500001/8df164f0-477d-479c-9846-2059be35efac/736abacf-bea6-48a3-91f2-249737581cf1/1280x720/match/image.jpg",
            "link": "https://www.mercy.net/doctor/lara-taylor-fnp/"
        },
        {
            "title": "Jordan W. Swanson, MD, MSc | Children's Hospital of Philadelphia",
            "imageUrl": "https://www.chop.edu/sites/default/files/providers-new-swanson-jordan.jpg",
            "link": "https://www.chop.edu/doctors/swanson-jordan-w"
        }
    ],
    "credits": 1
}